LICENSE.rst
README.rst
pyproject.toml
setup.py
galaxie_eveloop.egg-info/PKG-INFO
galaxie_eveloop.egg-info/SOURCES.txt
galaxie_eveloop.egg-info/dependency_links.txt
galaxie_eveloop.egg-info/requires.txt
galaxie_eveloop.egg-info/top_level.txt
glxeveloop/__init__.py
glxeveloop/bus.py
glxeveloop/fps.py
glxeveloop/hooks.py
glxeveloop/timer.py
glxeveloop/loop/__init__.py
glxeveloop/loop/builder.py
glxeveloop/loop/handle_events.py
glxeveloop/loop/loop.py
glxeveloop/loop/mainloop.py
glxeveloop/loop/sequence.py
glxeveloop/loop/singleton.py
glxeveloop/loop/start.py
glxeveloop/loop/stop.py
glxeveloop/properties/__init__.py
glxeveloop/properties/debug.py
glxeveloop/properties/hooks.py
glxeveloop/properties/queue.py
glxeveloop/properties/running.py
glxeveloop/properties/timer.py
tests/test_builders.py
tests/test_bus.py
tests/test_debug.py
tests/test_fps.py
tests/test_hooks.py
tests/test_loop.py
tests/test_timer.py