Metadata-Version: 2.1
Name: galaxie-eveloop
Version: 0.1.5
Summary: Galaxie EveLoop is a low tech EventLoop, it contain minimalistic Bus and Loop
Author: Tuuux
License: WTFPL
Project-URL: Homepage, https://codeberg.org/Tuuux/galaxie-eveloop
Project-URL: Issues, https://codeberg.org/Tuuux/galaxie-eveloop/issues
Project-URL: Readthedocs, http://galaxie-eveloop.readthedocs.io
Project-URL: Changelog, https://codeberg.org/Tuuux/galaxie-eveloop/src/branch/master/CHANGELOG.rst
Keywords: Galaxie,Mainloop,Bus
Classifier: Environment :: Console
Classifier: Intended Audience :: Developers
Classifier: Topic :: Software Development :: Libraries :: Python Modules
Classifier: Programming Language :: Python
Classifier: Programming Language :: Python :: 3 :: Only
Requires-Python: >=3.0
License-File: LICENSE.rst
Requires-Dist: wheel
Provides-Extra: tests
Requires-Dist: coverage; extra == "tests"
Requires-Dist: wheel; extra == "tests"
Requires-Dist: mock<4,>=1.0.1; python_version < "3.4" and extra == "tests"
